datasette_enrichments_opencage/__init__.py
datasette_enrichments_opencage-0.1.1.dist-info/LICENSE
datasette_enrichments_opencage-0.1.1.dist-info/METADATA
datasette_enrichments_opencage-0.1.1.dist-info/WHEEL
datasette_enrichments_opencage-0.1.1.dist-info/entry_points.txt
datasette_enrichments_opencage-0.1.1.dist-info/top_level.txt
datasette_enrichments_opencage-0.1.1.dist-info/RECORD
