Metadata-Version: 2.1
Name: datasette-enrichments-opencage
Version: 0.1.1
Summary: Geocoding enrichment using OpenCage
Author: Simon Willison
License: Apache-2.0
Project-URL: Homepage, https://github.com/datasette/datasette-enrichments-opencage
Project-URL: Changelog, https://github.com/datasette/datasette-enrichments-opencage/releases
Project-URL: Issues, https://github.com/datasette/datasette-enrichments-opencage/issues
Project-URL: CI, https://github.com/datasette/datasette-enrichments-opencage/actions
Classifier: Framework :: Datasette
Classifier: License :: OSI Approved :: Apache Software License
Requires-Python: >=3.8
License-File: LICENSE
Requires-Dist: datasette
Requires-Dist: datasette-enrichments >=0.2
Requires-Dist: sqlite-utils
Provides-Extra: test
Requires-Dist: pytest ; extra == 'test'
Requires-Dist: pytest-asyncio ; extra == 'test'
Requires-Dist: pytest-httpx ; extra == 'test'
